remyxai/__init__.py
remyxai/api/__init__.py
remyxai/api/datasets.py
remyxai/api/deployment.py
remyxai/api/evaluations.py
remyxai/api/inference.py
remyxai/api/models.py
remyxai/api/myxboard.py
remyxai/api/search.py
remyxai/api/tasks.py
remyxai/api/user.py
remyxai/cli/__init__.py
remyxai/cli/commands.py
remyxai/cli/dataset_actions.py
remyxai/cli/deployment_actions.py
remyxai/cli/evaluation_actions.py
remyxai/cli/search_actions.py
remyxai/client/__init__.py
remyxai/client/myxboard.py
remyxai/client/remyx_client.py
remyxai/client/search.py
remyxai/utils/__init__.py
remyxai/utils/helpers.py
remyxai/utils/myxboard.py
remyxai/utils/validators.py
remyxai-0.2.0.dist-info/licenses/LICENSE
remyxai-0.2.0.dist-info/METADATA
remyxai-0.2.0.dist-info/WHEEL
remyxai-0.2.0.dist-info/entry_points.txt
remyxai-0.2.0.dist-info/top_level.txt
remyxai-0.2.0.dist-info/RECORD
