Metadata-Version: 2.4
Name: remyxai
Version: 0.2.0
Classifier: Programming Language :: Python :: 3
Classifier: License :: OSI Approved :: MIT License
Classifier: Operating System :: OS Independent
Requires-Python: >=3.6
License-File: LICENSE
Requires-Dist: numpy
Requires-Dist: onnx
Requires-Dist: onnxruntime
Requires-Dist: pillow
Requires-Dist: requests
Requires-Dist: tqdm
Requires-Dist: tritonclient[all]
Requires-Dist: huggingface_hub
Requires-Dist: datasets
Requires-Dist: pandas
Dynamic: classifier
Dynamic: description
Dynamic: description-content-type
Dynamic: license-file
Dynamic: requires-dist
Dynamic: requires-python
